DjangoEasyScoping/ScopingMixin.py
DjangoEasyScoping/__init__.py
django_easy_scoping-1.13.dist-info/METADATA
django_easy_scoping-1.13.dist-info/RECORD
django_easy_scoping-1.13.dist-info/WHEEL
django_easy_scoping-1.13.dist-info/top_level.txt
