Metadata-Version: 2.1
Name: django-easy-scoping
Version: 1.13
Summary: A mixin to allow users to create scopes on Django models.
Home-page: https://github.com/net-prophet/django-easy-scoping
Author: Net Prophet
Author-email: wellsroberte@gmail.com
License: BSD
Project-URL: Usage, https://net-prophet.github.io/django-easy-scoping/docs/usage.html
Project-URL: Docs, https://net-prophet.github.io/django-easy-scoping/
Project-URL: API, https://net-prophet.github.io/django-easy-scoping/docs/api.html
Keywords: django python scope scoping aggregate
Platform: UNKNOWN
Classifier: Development Status :: 5 - Production/Stable
Classifier: Intended Audience :: Developers
Classifier: Topic :: Software Development :: Build Tools
Classifier: Programming Language :: Python :: 2
Classifier: Programming Language :: Python :: 2.7
Classifier: Programming Language :: Python :: 3
Classifier: Programming Language :: Python :: 3.1
Classifier: Programming Language :: Python :: 3.5
Classifier: Programming Language :: Python :: 3.6
Requires-Python: >=2.7, !=3.0.*, !=3.1.*, !=3.2.*, !=3.3.*
Requires-Dist: Django (<3.0,>=1.11)
